odoo9_addon_web_tree_image-9.0.1.1.0-py2.7-nspkg.pth
odoo_addons/web_tree_image/__openerp__.py
odoo_addons/web_tree_image/__init__.py
odoo_addons/web_tree_image/README.rst
odoo_addons/web_tree_image/view/assets.xml
odoo_addons/web_tree_image/static/description/icon.png
odoo_addons/web_tree_image/static/src/js/web_tree_image.js
odoo_addons/web_tree_image/static/src/xml/widget.xml
odoo9_addon_web_tree_image-9.0.1.1.0.dist-info/top_level.txt
odoo9_addon_web_tree_image-9.0.1.1.0.dist-info/WHEEL
odoo9_addon_web_tree_image-9.0.1.1.0.dist-info/RECORD
odoo9_addon_web_tree_image-9.0.1.1.0.dist-info/metadata.json
odoo9_addon_web_tree_image-9.0.1.1.0.dist-info/DESCRIPTION.rst
odoo9_addon_web_tree_image-9.0.1.1.0.dist-info/METADATA
odoo9_addon_web_tree_image-9.0.1.1.0.dist-info/namespace_packages.txt
