Metadata-Version: 2.0
Name: odoo9-addon-web-tree-image
Version: 9.0.1.1.0
Summary: Show images in tree views
Home-page: https://github.com/OCA/Web
Author: UNKNOWN
Author-email: UNKNOWN
License: AGPL-3
Platform: UNKNOWN
Requires-Dist: odoo (<9.1a,>=9.0a)
Classifier: Programming Language :: Python :: 2.7
Classifier: Framework :: Odoo
Classifier: License :: OSI Approved :: GNU Affero General Public License v3
